incogniton/__init__.py
incogniton/api/__init__.py
incogniton/api/client.py
incogniton/browser/__init__.py
incogniton/browser/browser.py
incogniton/config/__init__.py
incogniton/config/defaults.py
incogniton/models/__init__.py
incogniton/models/api_types.py
incogniton/models/browser_profile_types.py
incogniton/models/common_types.py
incogniton/utils/__init__.py
incogniton/utils/delay.py
incogniton/utils/http/__init__.py
incogniton/utils/http/agent.py
incogniton/utils/http/errors.py
incogniton/utils/loading_animation.py
incogniton/utils/loading_indicator.py
incogniton/utils/logger.py
incogniton-0.2.7.dist-info/METADATA
incogniton-0.2.7.dist-info/WHEEL
incogniton-0.2.7.dist-info/RECORD
