Metadata-Version: 2.3
Name: incogniton
Version: 0.2.7
Summary: Python client for Incogniton API
Author: Yusuf Abdulhafeez
Author-email: yusuf@incogniton.com
Requires-Python: >=3.9,<4.0
Classifier: Programming Language :: Python :: 3
Classifier: Programming Language :: Python :: 3.9
Classifier: Programming Language :: Python :: 3.10
Classifier: Programming Language :: Python :: 3.11
Classifier: Programming Language :: Python :: 3.12
Classifier: Programming Language :: Python :: 3.13
Requires-Dist: httpx (>=0.28.1,<0.29.0)
Requires-Dist: playwright (>=1.53.0,<2.0.0)
Requires-Dist: pydantic (>=2.6.4,<3.0.0)
Requires-Dist: selenium (>=4.35.0,<5.0.0)
Requires-Dist: urllib3 (>=2.5.0,<3.0.0)
